{
  "Pranav_MP": [
    {
      "date": "2026-02-13",
      "count": 43,
      "easy": 20,
      "medium": 21,
      "hard": 2,
      "timestamp": "2026-02-13T00:00:00Z"
    },
    {
      "date": "2026-02-14",
      "count": 43,
      "easy": 20,
      "medium": 21,
      "hard": 2,
      "timestamp": "2026-02-14T00:00:00Z"
    }
  ],
  "khizer12": [
    {
      "date": "2026-02-13",
      "count": 180,
      "easy": 52,
      "medium": 106,
      "hard": 22,
      "timestamp": "2026-02-13T00:00:00Z"
    },
    {
      "date": "2026-02-14",
      "count": 180,
      "easy": 52,
      "medium": 106,
      "hard": 22,
      "timestamp": "2026-02-14T00:00:00Z"
    }
  ],
  "khrshtt": [
    {
      "date": "2026-02-13",
      "count": 107,
      "easy": 51,
      "medium": 52,
      "hard": 4,
      "timestamp": "2026-02-13T00:00:00Z"
    },
    {
      "date": "2026-02-14",
      "count": 107,
      "easy": 51,
      "medium": 52,
      "hard": 4,
      "timestamp": "2026-02-14T00:00:00Z"
    },
    {
      "date": "2026-02-14",
      "timestamp": "2026-02-14T08:35:09Z",
      "count": 108,
      "easy": 51,
      "medium": 53,
      "hard": 4
    }
  ],
  "theLumberJack79": [
    {
      "date": "2026-02-13",
      "count": 92,
      "easy": 39,
      "medium": 50,
      "hard": 3,
      "timestamp": "2026-02-13T00:00:00Z"
    },
    {
      "date": "2026-02-14",
      "count": 92,
      "easy": 39,
      "medium": 50,
      "hard": 3,
      "timestamp": "2026-02-14T00:00:00Z"
    },
    {
      "date": "2026-02-14",
      "timestamp": "2026-02-14T10:28:51Z",
      "count": 93,
      "easy": 39,
      "medium": 51,
      "hard": 3
    }
  ]
}